CHANGES.txt
MANIFEST.in
README.txt
setup.cfg
setup.py
tw/__init__.py
tw.uploadify.egg-info/PKG-INFO
tw.uploadify.egg-info/SOURCES.txt
tw.uploadify.egg-info/dependency_links.txt
tw.uploadify.egg-info/entry_points.txt
tw.uploadify.egg-info/namespace_packages.txt
tw.uploadify.egg-info/not-zip-safe
tw.uploadify.egg-info/requires.txt
tw.uploadify.egg-info/top_level.txt
tw/uploadify/__init__.py
tw/uploadify/release.py
tw/uploadify/samples.py
tw/uploadify/widgets.py
tw/uploadify/static/css/uploadify.css
tw/uploadify/static/images/cancel.png
tw/uploadify/static/js/jquery.uploadify.v2.1.4.min.js
tw/uploadify/static/js/swfobject.js
tw/uploadify/static/swf/expressInstall.swf
tw/uploadify/static/swf/uploadify.swf