Metadata-Version: 1.0
Name: tw.uploadify
Version: 0.1a3
Summary: upload files with progress informations
Home-page: UNKNOWN
Author: Nicolas Laurance
Author-email: nicolas[dot]laurance[at]gmail[dot]com
License: UNKNOWN
Keywords: toscawidgets.widgets,jquery,uploadify,progress bar
Platform: UNKNOWN
Classifier: Development Status :: 3 - Alpha
Classifier: Environment :: Web Environment
Classifier: Environment :: Web Environment :: ToscaWidgets
Classifier: Topic :: Software Development :: Libraries :: Python Modules
Classifier: Topic :: Software Development :: Widget Sets
Classifier: Intended Audience :: Developers
Classifier: Operating System :: OS Independent
Classifier: Programming Language :: Python
Classifier: Framework :: TurboGears :: Widgets
Classifier: License :: OSI Approved :: MIT License
